pophealth_observatory/__init__.py
pophealth_observatory/brfss.py
pophealth_observatory/laboratory_pesticides.py
pophealth_observatory/observatory.py
pophealth_observatory/pesticide_context.py
pophealth_observatory/pesticide_ingestion.py
pophealth_observatory/validation.py
pophealth_observatory/rag/__init__.py
pophealth_observatory/rag/config.py
pophealth_observatory/rag/embeddings.py
pophealth_observatory/rag/index.py
pophealth_observatory/rag/pipeline.py
pophealth_observatory-0.7.0.dist-info/LICENSE
pophealth_observatory-0.7.0.dist-info/METADATA
pophealth_observatory-0.7.0.dist-info/WHEEL
pophealth_observatory-0.7.0.dist-info/top_level.txt
pophealth_observatory-0.7.0.dist-info/RECORD
