Metadata-Version: 2.1
Name: pophealth-observatory
Version: 0.7.0
Summary: Open-source population health & nutrition analytics toolkit (NHANES focus)
Author: PopHealth Observatory Team
License: MIT
Project-URL: Homepage, https://github.com/paulboys/PopHealth-Observatory
Project-URL: Source, https://github.com/paulboys/PopHealth-Observatory
Project-URL: Issues, https://github.com/paulboys/PopHealth-Observatory/issues
Project-URL: Documentation, https://paulboys.github.io/PopHealth-Observatory/
Classifier: Development Status :: 3 - Alpha
Classifier: Intended Audience :: Science/Research
Classifier: License :: OSI Approved :: MIT License
Classifier: Programming Language :: Python :: 3
Classifier: Programming Language :: Python :: 3.8
Classifier: Programming Language :: Python :: 3.9
Classifier: Programming Language :: Python :: 3.10
Classifier: Programming Language :: Python :: 3.11
Classifier: Programming Language :: Python :: 3.12
Classifier: Topic :: Scientific/Engineering :: Information Analysis
Classifier: Topic :: Scientific/Engineering :: Medical Science Apps.
Requires-Python: >=3.8
License-File: LICENSE
Requires-Dist: pandas>=1.3.0
Requires-Dist: numpy>=1.20.0
Requires-Dist: scipy>=1.9.0
Requires-Dist: requests>=2.25.0
Requires-Dist: matplotlib>=3.4.0
Requires-Dist: seaborn>=0.11.0
Requires-Dist: plotly>=5.3.0
Requires-Dist: ipywidgets>=7.6.0
Requires-Dist: pyarrow>=18.0.0
Requires-Dist: beautifulsoup4>=4.9.0
Requires-Dist: lxml>=4.6.0
Requires-Dist: pillow>=10.0.0
Requires-Dist: streamlit>=1.30.0
Requires-Dist: statsmodels>=0.13.0
Provides-Extra: dev
Requires-Dist: pytest>=7.0.0; extra == "dev"
Requires-Dist: pytest-cov>=4.0.0; extra == "dev"
Requires-Dist: build; extra == "dev"
Requires-Dist: twine; extra == "dev"
Requires-Dist: ruff>=0.4.0; extra == "dev"
Requires-Dist: black>=24.3.0; extra == "dev"
Requires-Dist: coverage>=7.4.0; extra == "dev"
Requires-Dist: pre-commit>=3.5.0; extra == "dev"
Provides-Extra: docs
Requires-Dist: mkdocs>=1.5.0; extra == "docs"
Requires-Dist: mkdocs-material>=9.5.0; extra == "docs"
Provides-Extra: rag
Requires-Dist: sentence-transformers>=2.7.0; extra == "rag"
Requires-Dist: faiss-cpu>=1.7.4; platform_system != "Windows" and extra == "rag"
